ossom/__init__.py
ossom/audio.py
ossom/configurations.py
ossom/monitor.py
ossom/streamer.py
ossom/utils/__init__.py
ossom/utils/colore.py
ossom/utils/freq.py
ossom/utils/logger.py
ossom/utils/maths.py
ossom/utils/wavefile.py
OsSom-0.1.0a0.dist-info/LICENSE
OsSom-0.1.0a0.dist-info/METADATA
OsSom-0.1.0a0.dist-info/WHEEL
OsSom-0.1.0a0.dist-info/top_level.txt
OsSom-0.1.0a0.dist-info/RECORD
